django_xapp_render-0.0.7.dist-info/METADATA
django_xapp_render-0.0.7.dist-info/RECORD
django_xapp_render-0.0.7.dist-info/WHEEL
django_xapp_render-0.0.7.dist-info/top_level.txt
xapp_render/__init__.py
xapp_render/models.py
xapp_render/signals.py
xapp_render/template_utils.py
xapp_render/tests.py
xapp_render/utils.py
xapp_render/version.py
xapp_render/templatetags/__init__.py
xapp_render/templatetags/xapp_render.py
xapp_render/templatetags/xapp_render_jinja2.py
